punish/__init__.py
punish/style.py
punish/type.py
enforce_pep8-0.0.12.dist-info/AUTHORS.md
enforce_pep8-0.0.12.dist-info/LICENSE.md
enforce_pep8-0.0.12.dist-info/METADATA
enforce_pep8-0.0.12.dist-info/WHEEL
enforce_pep8-0.0.12.dist-info/top_level.txt
enforce_pep8-0.0.12.dist-info/RECORD
