Metadata-Version: 2.1
Name: enforce-pep8
Version: 0.0.12
Summary: Package contains interfaces to enforce PEP8 coding conventions.
Home-page: https://github.com/vyahello/enforce-pep8
Author: Volodymyr Yahello
Author-email: vyahello@gmail.com
License: UNKNOWN
Platform: UNKNOWN
Classifier: Programming Language :: Python :: 3.6
Classifier: Programming Language :: Python :: 3.7
Classifier: Programming Language :: Python :: 3.8
Classifier: Programming Language :: Python :: 3.9
Classifier: License :: OSI Approved :: MIT License
Classifier: Operating System :: OS Independent
Requires-Python: >=3.6
License-File: LICENSE.md
License-File: AUTHORS.md
Requires-Dist: dataclasses (==0.6.0)
Requires-Dist: attrs (==19.3.0)
